LICENSE
README.md
setup.cfg
setup.py
django_pygmento.egg-info/PKG-INFO
django_pygmento.egg-info/SOURCES.txt
django_pygmento.egg-info/dependency_links.txt
django_pygmento.egg-info/requires.txt
django_pygmento.egg-info/top_level.txt
pygmento/__init__.py
pygmento/apps.py
pygmento/templatetags/__init__.py
pygmento/templatetags/pygmento.py